maseya/__init__.py
maseya/z3pr/__init__.py
maseya/z3pr/__main__.py
maseya/z3pr/color_f.py
maseya/z3pr/maseya_blend.py
maseya/z3pr/math_helper.py
maseya/z3pr/options.py
maseya/z3pr/palette_editor.py
maseya/z3pr/palette_randomizer.py
maseya/z3pr/snes_color.py
maseya/z3pr/data/dungeon.json
maseya/z3pr/data/hud.json
maseya/z3pr/data/link_sprite.json
maseya/z3pr/data/overworld.json
maseya/z3pr/data/shield.json
maseya/z3pr/data/sword.json
maseya_z3pr-1.0.0rc1.dist-info/LICENSE.md
maseya_z3pr-1.0.0rc1.dist-info/METADATA
maseya_z3pr-1.0.0rc1.dist-info/WHEEL
maseya_z3pr-1.0.0rc1.dist-info/top_level.txt
maseya_z3pr-1.0.0rc1.dist-info/RECORD
