Metadata-Version: 2.1
Name: maseya-z3pr
Version: 1.0.0rc1
Summary: Randomize palette data for Legend of Zelda: A Link to the Past.
Home-page: https://github.com/maseya/z3pr-py
Author: Nelson Garcia
Author-email: swr.ngarcia@gmail.com
License: UNKNOWN
Platform: UNKNOWN
Classifier: Development Status :: 1 - Planning
Classifier: Environment :: Console
Classifier: Intended Audience :: Developers
Classifier: Intended Audience :: End Users/Desktop
Classifier: License :: OSI Approved :: GNU Lesser General Public License v3 or later (LGPLv3+)
Classifier: Natural Language :: English
Classifier: Operating System :: OS Independent
Classifier: Programming Language :: Python :: 3.4
Classifier: Topic :: Games/Entertainment
Classifier: Topic :: Multimedia :: Graphics :: Editors
Classifier: Topic :: Utilities
Requires-Python: >=3.4
